senses/__init__.py
senses-0.1.0.dist-info/METADATA
senses-0.1.0.dist-info/WHEEL
senses-0.1.0.dist-info/RECORD
